[
    {
        "date": "2026-07-20",
        "day": "Monday",
        "moon_phase": "Error fetching data: HTTPSConnectionPool(host='ssd.jpl.nasa.gov', port=443): Max retries exceeded with url: /api/horizons.api?format=text&COMMAND='301'&EPHEM_TYPE='OBSERVER'&CENTER='500@399'&START_TIME='2026-07-20%2000:00'&STOP_TIME='2026-07-20%2023:59'&STEP_SIZE='1%20d'&QUANTITIES='1,31' (Caused by ConnectTimeoutError(<HTTPSConnection(host='ssd.jpl.nasa.gov', port=443) at 0x7f896e83f230>, 'Connection to ssd.jpl.nasa.gov timed out. (connect timeout=None)'))",
        "moon_phase_meaning": "N/A",
        "lunar_mansion_name": "N/A",
        "lunar_mansion_meaning": "N/A"
    },
    {
        "date": "2026-07-21",
        "day": "Tuesday",
        "moon_phase": "Error fetching data: HTTPSConnectionPool(host='ssd.jpl.nasa.gov', port=443): Max retries exceeded with url: /api/horizons.api?format=text&COMMAND='301'&EPHEM_TYPE='OBSERVER'&CENTER='500@399'&START_TIME='2026-07-21%2000:00'&STOP_TIME='2026-07-21%2023:59'&STEP_SIZE='1%20d'&QUANTITIES='1,31' (Caused by ConnectTimeoutError(<HTTPSConnection(host='ssd.jpl.nasa.gov', port=443) at 0x7f896e7420d0>, 'Connection to ssd.jpl.nasa.gov timed out. (connect timeout=None)'))",
        "moon_phase_meaning": "N/A",
        "lunar_mansion_name": "N/A",
        "lunar_mansion_meaning": "N/A"
    },
    {
        "date": "2026-07-22",
        "day": "Wednesday",
        "moon_phase": "Error fetching data: HTTPSConnectionPool(host='ssd.jpl.nasa.gov', port=443): Max retries exceeded with url: /api/horizons.api?format=text&COMMAND='301'&EPHEM_TYPE='OBSERVER'&CENTER='500@399'&START_TIME='2026-07-22%2000:00'&STOP_TIME='2026-07-22%2023:59'&STEP_SIZE='1%20d'&QUANTITIES='1,31' (Caused by ConnectTimeoutError(<HTTPSConnection(host='ssd.jpl.nasa.gov', port=443) at 0x7f896e742990>, 'Connection to ssd.jpl.nasa.gov timed out. (connect timeout=None)'))",
        "moon_phase_meaning": "N/A",
        "lunar_mansion_name": "N/A",
        "lunar_mansion_meaning": "N/A"
    },
    {
        "date": "2026-07-23",
        "day": "Thursday",
        "moon_phase": "Error fetching data: HTTPSConnectionPool(host='ssd.jpl.nasa.gov', port=443): Max retries exceeded with url: /api/horizons.api?format=text&COMMAND='301'&EPHEM_TYPE='OBSERVER'&CENTER='500@399'&START_TIME='2026-07-23%2000:00'&STOP_TIME='2026-07-23%2023:59'&STEP_SIZE='1%20d'&QUANTITIES='1,31' (Caused by ConnectTimeoutError(<HTTPSConnection(host='ssd.jpl.nasa.gov', port=443) at 0x7f896e742c10>, 'Connection to ssd.jpl.nasa.gov timed out. (connect timeout=None)'))",
        "moon_phase_meaning": "N/A",
        "lunar_mansion_name": "N/A",
        "lunar_mansion_meaning": "N/A"
    },
    {
        "date": "2026-07-24",
        "day": "Friday",
        "moon_phase": "Error fetching data: HTTPSConnectionPool(host='ssd.jpl.nasa.gov', port=443): Max retries exceeded with url: /api/horizons.api?format=text&COMMAND='301'&EPHEM_TYPE='OBSERVER'&CENTER='500@399'&START_TIME='2026-07-24%2000:00'&STOP_TIME='2026-07-24%2023:59'&STEP_SIZE='1%20d'&QUANTITIES='1,31' (Caused by ConnectTimeoutError(<HTTPSConnection(host='ssd.jpl.nasa.gov', port=443) at 0x7f896e742c10>, 'Connection to ssd.jpl.nasa.gov timed out. (connect timeout=None)'))",
        "moon_phase_meaning": "N/A",
        "lunar_mansion_name": "N/A",
        "lunar_mansion_meaning": "N/A"
    },
    {
        "date": "2026-07-25",
        "day": "Saturday",
        "moon_phase": "Error fetching data: HTTPSConnectionPool(host='ssd.jpl.nasa.gov', port=443): Max retries exceeded with url: /api/horizons.api?format=text&COMMAND='301'&EPHEM_TYPE='OBSERVER'&CENTER='500@399'&START_TIME='2026-07-25%2000:00'&STOP_TIME='2026-07-25%2023:59'&STEP_SIZE='1%20d'&QUANTITIES='1,31' (Caused by ConnectTimeoutError(<HTTPSConnection(host='ssd.jpl.nasa.gov', port=443) at 0x7f896e742350>, 'Connection to ssd.jpl.nasa.gov timed out. (connect timeout=None)'))",
        "moon_phase_meaning": "N/A",
        "lunar_mansion_name": "N/A",
        "lunar_mansion_meaning": "N/A"
    },
    {
        "date": "2026-07-26",
        "day": "Sunday",
        "moon_phase": "Error fetching data: HTTPSConnectionPool(host='ssd.jpl.nasa.gov', port=443): Max retries exceeded with url: /api/horizons.api?format=text&COMMAND='301'&EPHEM_TYPE='OBSERVER'&CENTER='500@399'&START_TIME='2026-07-26%2000:00'&STOP_TIME='2026-07-26%2023:59'&STEP_SIZE='1%20d'&QUANTITIES='1,31' (Caused by ConnectTimeoutError(<HTTPSConnection(host='ssd.jpl.nasa.gov', port=443) at 0x7f896e7425d0>, 'Connection to ssd.jpl.nasa.gov timed out. (connect timeout=None)'))",
        "moon_phase_meaning": "N/A",
        "lunar_mansion_name": "N/A",
        "lunar_mansion_meaning": "N/A"
    }
]